mne_hfo/__init__.py
mne_hfo/base.py
mne_hfo/compare.py
mne_hfo/config.py
mne_hfo/detect.py
mne_hfo/hodetect.py
mne_hfo/io.py
mne_hfo/posthoc.py
mne_hfo/score.py
mne_hfo/simulate.py
mne_hfo/sklearn.py
mne_hfo/stats.py
mne_hfo/utils.py
tests/__init__.py
tests/conftest.py
tests/test_compare.py
tests/test_detect.py
tests/test_io.py
tests/test_posthoc.py
tests/test_score.py
tests/test_simulation.py
tests/test_utils.py
mne_hfo-0.2.dist-info/LICENSE
mne_hfo-0.2.dist-info/METADATA
mne_hfo-0.2.dist-info/WHEEL
mne_hfo-0.2.dist-info/top_level.txt
mne_hfo-0.2.dist-info/RECORD
