Metadata-Version: 2.1
Name: mne-hfo
Version: 0.2
Summary: MNE-HFO: Facilitates estimation/detection of high-frequency oscillationevents on iEEG data with MNE-Python, MNE-BIDS and scikit-learn.
Home-page: https://mne.tools/mne-hfo/stable/index.html
Maintainer: Adam Li
Maintainer-email: adam2392@gmail.com
License: BSD (3-clause)
Download-URL: https://github.com/mne-tools/mne-hfo.git
Project-URL: Documentation, https://mne.tools/mne-hfo/stable/index.html
Project-URL: Bug Reports, https://github.com/mne-tools/mne-hfo/issues
Project-URL: Source, https://github.com/mne-tools/mne-hfo
Platform: any
Classifier: Intended Audience :: Science/Research
Classifier: Intended Audience :: Developers
Classifier: License :: OSI Approved
Classifier: Programming Language :: Python
Classifier: Topic :: Software Development
Classifier: Topic :: Scientific/Engineering
Classifier: Operating System :: POSIX
Classifier: Operating System :: Unix
Classifier: Operating System :: MacOS
Classifier: Programming Language :: Python :: 3.6
Classifier: Programming Language :: Python :: 3.7
Classifier: Programming Language :: Python :: 3.8
Classifier: Programming Language :: Python :: 3.9
Requires-Python: ~=3.6
Requires-Dist: mne (>=0.23)
Requires-Dist: mne-bids (>=0.7)
Requires-Dist: numpy (>=1.14)
Requires-Dist: scipy (>=0.18.1)
Requires-Dist: scikit-learn (>=0.23)
Requires-Dist: tqdm
Requires-Dist: pandas (>=0.23.4)
Provides-Extra: full
Requires-Dist: joblib (>=1.0.0) ; extra == 'full'
Requires-Dist: matplotlib ; extra == 'full'
